{
    "Changes": [
        //---------------------------- ITEM DATA ------------------------------------------// 
        {
            "Action": "EditData",
            "Target": "Data/Objects",
            "Entries": {
                "{{ModID}}.Items.VoidLavaSnailEgg": {
                    "Name": "{{ModID}}.Items.VoidLavaSnailEgg",
                    "DisplayName": "{{i18n:Items.VoidLavaSnailEgg.Title}}",
                    "Description": "{{i18n:Items.VoidLavaSnailEgg.Description}}",
                    "Type": "Basic",
                    "Category": -5,
                    "Price": 400,
                    "Edibility": -300,
                    "Buff": null,
                    "IsDrink": false,
                    "ExcludeFromFishingCollection": "{{Items Required For Perfection}}",
                    "ContextTags": [ "color_red", "color_black", "egg_item", "large_egg_item" ],
                    "Texture": "{{InternalAssetKey: assets/Items/Objects.png}}",
                    "SpriteIndex": 7
                }               
            }
        },
        {
            "Action": "EditData",
            "Target": "Data/Objects",
            "Entries": {
                "{{ModID}}.Items.GoldenVoidLavaSnailEgg": {
                    "Name": "{{ModID}}.Items.GoldenVoidLavaSnailEgg",
                    "DisplayName": "{{i18n:Items.GoldenVoidLavaSnailEgg.Title}}",
                    "Description": "{{i18n:Items.GoldenVoidLavaSnailEgg.Description}}",
                    "Type": "Basic",
                    "Category": -5,
                    "Price": 5000,
                    "Edibility": -300,
                    "Buff": null,
                    "IsDrink": false,
                    "ExcludeFromShippingCollection": true,
                    "ContextTags": [ "color_gold", "egg_item", "large_egg_item" ],
                    "Texture": "{{InternalAssetKey: assets/Items/Objects.png}}",
                    "SpriteIndex": 10
                }               
            }
        }
    ]
}